LICENSE.txt
README.md
setup.py
easytradetesting/BackTestContext.py
easytradetesting/BackTestEngine.py
easytradetesting/BackTestOrder.py
easytradetesting/BackTestResult.py
easytradetesting/DataFetcher.py
easytradetesting/DataSource.py
easytradetesting/MySqlDataSource.py
easytradetesting/__init__.py
easytradetesting.egg-info/PKG-INFO
easytradetesting.egg-info/SOURCES.txt
easytradetesting.egg-info/dependency_links.txt
easytradetesting.egg-info/requires.txt
easytradetesting.egg-info/top_level.txt
easytradetesting/api/MarketApi.py
easytradetesting/api/TradeApi.py
easytradetesting/api/__init__.py