Metadata-Version: 2.1
Name: easytradetesting
Version: 0.1.3
Summary: The simple sdk for testing strategy
Home-page: 
Author: EasyTrade Tech Team
Author-email: tech_team@easytrade.cloud
License: MIT
Classifier: License :: OSI Approved :: MIT License
Classifier: Programming Language :: Python
Classifier: Programming Language :: Python :: 3
Classifier: Programming Language :: Python :: 3.8
Classifier: Programming Language :: Python :: Implementation :: CPython
Classifier: Programming Language :: Python :: Implementation :: PyPy
Requires-Python: >=3.8.0
License-File: LICENSE.txt
